pyqrlib/__init__.py
pyqrlib/app.py
pyqrlib-0.0.1.dist-info/LICENSE
pyqrlib-0.0.1.dist-info/METADATA
pyqrlib-0.0.1.dist-info/WHEEL
pyqrlib-0.0.1.dist-info/top_level.txt
pyqrlib-0.0.1.dist-info/RECORD
